qulab/__init__.py
qulab/__main__.py
qulab/typing.py
qulab/utils.py
qulab/version.py
qulab/cli/__init__.py
qulab/cli/commands.py
qulab/cli/config.py
qulab/cli/decorators.py
qulab/executor/__init__.py
qulab/executor/analyze.py
qulab/executor/cli.py
qulab/executor/load.py
qulab/executor/registry.py
qulab/executor/schedule.py
qulab/executor/storage.py
qulab/executor/template.py
qulab/executor/utils.py
qulab/monitor/__init__.py
qulab/monitor/__main__.py
qulab/monitor/config.py
qulab/monitor/dataset.py
qulab/monitor/event_queue.py
qulab/monitor/mainwindow.py
qulab/monitor/monitor.py
qulab/monitor/ploter.py
qulab/monitor/qt_compat.py
qulab/monitor/toolbar.py
qulab/scan/__init__.py
qulab/scan/curd.py
qulab/scan/models.py
qulab/scan/optimize.py
qulab/scan/query.py
qulab/scan/record.py
qulab/scan/scan.py
qulab/scan/server.py
qulab/scan/space.py
qulab/scan/utils.py
qulab/storage/__init__.py
qulab/storage/__main__.py
qulab/storage/base_dataset.py
qulab/storage/chunk.py
qulab/storage/dataset.py
qulab/storage/file.py
qulab/storage/storage.py
qulab/storage/backend/__init__.py
qulab/storage/backend/redis.py
qulab/storage/models/__init__.py
qulab/storage/models/base.py
qulab/storage/models/config.py
qulab/storage/models/file.py
qulab/storage/models/ipy.py
qulab/storage/models/models.py
qulab/storage/models/record.py
qulab/storage/models/report.py
qulab/storage/models/tag.py
qulab/sys/__init__.py
qulab/sys/chat.py
qulab/sys/ipy_events.py
qulab/sys/progress.py
qulab/sys/device/__init__.py
qulab/sys/device/basedevice.py
qulab/sys/device/loader.py
qulab/sys/device/utils.py
qulab/sys/drivers/FakeInstrument.py
qulab/sys/drivers/__init__.py
qulab/sys/net/__init__.py
qulab/sys/net/bencoder.py
qulab/sys/net/cli.py
qulab/sys/net/dhcp.py
qulab/sys/net/dhcpd.py
qulab/sys/net/kad.py
qulab/sys/net/kcp.py
qulab/sys/net/nginx.py
qulab/sys/rpc/__init__.py
qulab/sys/rpc/client.py
qulab/sys/rpc/exceptions.py
qulab/sys/rpc/msgpack.py
qulab/sys/rpc/msgpack.pyi
qulab/sys/rpc/router.py
qulab-2.12.2.dist-info/licenses/LICENSE
qulab-2.12.2.dist-info/METADATA
qulab-2.12.2.dist-info/WHEEL
qulab-2.12.2.dist-info/entry_points.txt
qulab-2.12.2.dist-info/top_level.txt
qulab-2.12.2.dist-info/RECORD
