Metadata-Version: 2.4
Name: QuLab
Version: 2.12.2
Summary: contral instruments and manage data
Author-email: feihoo87 <feihoo87@gmail.com>
Maintainer-email: feihoo87 <feihoo87@gmail.com>
License: MIT
Project-URL: Homepage, https://github.com/feihoo87/QuLab
Project-URL: Bug Reports, https://github.com/feihoo87/QuLab/issues
Project-URL: Source, https://github.com/feihoo87/QuLab/
Keywords: experiment,laboratory
Classifier: Development Status :: 5 - Production/Stable
Classifier: Intended Audience :: Developers
Classifier: Intended Audience :: Science/Research
Classifier: License :: OSI Approved :: MIT License
Classifier: Operating System :: Microsoft :: Windows
Classifier: Operating System :: POSIX :: Linux
Classifier: Operating System :: MacOS :: MacOS X
Classifier: Topic :: Scientific/Engineering :: Interface Engine/Protocol Translator
Classifier: Programming Language :: Python
Classifier: Programming Language :: Python :: 3.10
Classifier: Programming Language :: Python :: 3.11
Classifier: Programming Language :: Python :: 3.12
Requires-Python: >=3.10
License-File: LICENSE
Requires-Dist: blinker>=1.4
Requires-Dist: click>=7.1.2
Requires-Dist: dill>=0.3.6
Requires-Dist: GitPython>=3.1.14
Requires-Dist: ipython>=7.4.0
Requires-Dist: ipywidgets>=7.4.2
Requires-Dist: loguru>=0.7.2
Requires-Dist: matplotlib>=3.7.2
Requires-Dist: msgpack>=1.0.5
Requires-Dist: nevergrad>=1.0.2
Requires-Dist: numpy>=1.13.3
Requires-Dist: ply>=3.11
Requires-Dist: pyperclip>=1.8.2
Requires-Dist: pyzmq>=25.1.0
Requires-Dist: qlisp>=1.1.4
Requires-Dist: qlispc>=1.1.8
Requires-Dist: qlispreg>=0.0.1
Requires-Dist: scipy>=1.0.0
Requires-Dist: scikit-optimize>=0.9.0
Requires-Dist: SQLAlchemy>=2.0.19
Requires-Dist: watchdog>=4.0.0
Requires-Dist: wath>=1.1.6
Requires-Dist: waveforms>=1.9.4
Requires-Dist: rich>=14.0.0
Provides-Extra: full
Requires-Dist: paramiko>=3.5.1; extra == "full"
Requires-Dist: uvloop>=0.19.0; extra == "full"
Dynamic: license-file
